Workbook

Sheet Data
A1: Activity Report
A4: User | B4: Team | C4: Project name | D4: Company name | E4: Task issue ID | F4: Task name | G4: Activity description | H4: Activity date | I4: Start time | J4: End time | K4: Length | L4: Work type
A5: Zoltán Benjámin Zakota | B5: =IF(COUNTIF(Team!$A$2:$A$18,A5)>0,"CPS","") | C5: Synlab SDN | D5: Synlab | E5: 1002406 | F5: SDN-2406 - UK: SA Support (SPS, RM) | G5: JIRAID:110750 | H5: 46113 | K5: 1 | L5: Billable work
A6: Olívia Janka Bernát | B6: =IF(COUNTIF(Team!$A$2:$A$18,A6)>0,"CPS","") | C6: Synlab SDN | D6: Synlab | E6: 1001965 | F6: SDN-1965 - BA task general | G6: JIRAID:110740 follow ups, reviews | H6: 46113 | K6: 1 | L6: Billable work
A7: Marcell Kovács | B7: =IF(COUNTIF(Team!$A$2:$A$18,A7)>0,"CPS","") | C7: Cloud Platform Services | D7: Sonrisa | E7: 193502 | F7: ColosseumDental | H7: 46113 | K7: 4 | L7: Billable work
A8: Ádám Bálint | B8: =IF(COUNTIF(Team!$A$2:$A$18,A8)>0,"CPS","") | C8: Direct Travel Reporting Tool | D8: Direct Travel | F8: FE Dev | G8: DSM(s), NDE-2377, NDE-2457, Chat history takeover | H8: 46113 | K8: 8 | L8: Billable work
A9: Marcell Kovács | B9: =IF(COUNTIF(Team!$A$2:$A$18,A9)>0,"CPS","") | C9: Synlab Plasma (BigCommerce) | D9: Synlab | E9: 8000751 | F9: SD-751 - Create a MongoDB View that can provide BI Team results data requirement | G9: JIRAID:110749 | H9: 46113 | K9: 2.5 | L9: Billable work
A10: Bálint Lajos Török | B10: =IF(COUNTIF(Team!$A$2:$A$18,A10)>0,"CPS","") | C10: Cloud Platform Services | D10: Sonrisa | E10: 197976 | F10: IdomSoft - Faker Microsite Platform | G10: nkfh, VM hozzaferes ellenorzese, piler sync | H10: 46113 | K10: 2 | L10: Billable work
A11: Éva-Henrietta Nagy | B11: =IF(COUNTIF(Team!$A$2:$A$18,A11)>0,"CPS","") | C11: K11 Support | D11: Magyar Államkincstár | E11: 192284 | F11: [#990] Kormányzati szektorba sorolt egyéb szervezetek láthatóságának korlátozása, paraméterezéssel é | G11: + DSM + Heti jegyzetek előkészítése | H11: 46113 | K11: 2 | L11: Billable work
A12: Tibor Zsuró | B12: =IF(COUNTIF(Team!$A$2:$A$18,A12)>0,"CPS","") | C12: Lufthansa Netline - Crew | D12: Lufthansa | F12: General development | H12: 46113 | K12: 8 | L12: Billable work
A13: Péter Oláh | B13: =IF(COUNTIF(Team!$A$2:$A$18,A13)>0,"CPS","") | C13: Diligent Risk Essentials | D13: Diligent | E13: 186318 | F13: QA / Testing | H13: 46113 | K13: 8.5 | L13: Billable work
A14: Norbert Orbán | B14: =IF(COUNTIF(Team!$A$2:$A$18,A14)>0,"CPS","") | C14: SocialBudNewJira | D14: SocialBud | E14: 1003661 | F14: SB-3661 - Prod, UAT, Staging and QA deploy and testing | G14: JIRAID:30749 release/BUGFIX-009 prep | H14: 46113 | K14: 0.5 | L14: Billable work
A15: Attila Kovács | B15: =IF(COUNTIF(Team!$A$2:$A$18,A15)>0,"CPS","") | C15: Jumio AWS | D15: Jumio | E15: 181325 | F15: Development and operations | H15: 46113 | K15: 8 | L15: Billable work
A16: Bálint Lajos Török | B16: =IF(COUNTIF(Team!$A$2:$A$18,A16)>0,"CPS","") | C16: Cloud Platform Services | D16: Sonrisa | E16: 196631 | F16: Diligent - ARC BOS Sunset | G16: cmmc bug fixes, | H16: 46113 | K16: 6 | L16: Billable work
A17: Péter Brindzik | B17: =IF(COUNTIF(Team!$A$2:$A$18,A17)>0,"CPS","") | C17: Consultancy - Observer Service Remap | D17: OBSERVER | E17: 199756 | F17: Modit Knowledge Transfer Meetings | H17: 46113 | K17: 3 | L17: Billable work
A18: István Bánfi | B18: =IF(COUNTIF(Team!$A$2:$A$18,A18)>0,"CPS","") | C18: Consultancy - Observer Service Remap | D18: OBSERVER | E18: 199805 | F18: 3.6.ParlAI API bekötése - UAT | H18: 46113 | K18: 2 | L18: Billable work
A19: Bálint Lajos Török | B19: =IF(COUNTIF(Team!$A$2:$A$18,A19)>0,"CPS","") | C19: CPS Support | D19: Sonrisa | E19: 195325 | F19: MVMI OMNI - general availability collector ticket | H19: 46113 | K19: 6 | L19: Billable work
A20: Viktor Vörös | B20: =IF(COUNTIF(Team!$A$2:$A$18,A20)>0,"CPS","") | C20: K11 Production | D20: Magyar Államkincstár | E20: 198423 | F20: Felhasználó adatainak szerkesztése | H20: 46113 | K20: 1 | L20: Billable work
A21: Péter Brindzik | B21: =IF(COUNTIF(Team!$A$2:$A$18,A21)>0,"CPS","") | C21: Consultancy - Observer Service Remap | D21: OBSERVER | E21: 199755 | F21: Database Migration Plan | H21: 46113 | K21: 2 | L21: Billable work
A22: Dávid Pintér | B22: =IF(COUNTIF(Team!$A$2:$A$18,A22)>0,"CPS","") | C22: Lufthansa - OneRes | D22: Lufthansa | F22: OneRes Development | H22: 46113 | K22: 8 | L22: Billable work
A23: Blanka Cindel | B23: =IF(COUNTIF(Team!$A$2:$A$18,A23)>0,"CPS","") | C23: Sonrisa Office Management | D23: Sonrisa | F23: Insurance Meeting | H23: 46113 | K23: 0.5 | L23: Non-billable work
A24: Levente Gábos | B24: =IF(COUNTIF(Team!$A$2:$A$18,A24)>0,"CPS","") | C24: SocialBudNewJira | D24: SocialBud | E24: 1004630 | F24: SB-4630 - Error occurs when replying to a comment on a published post | G24: JIRAID:31163 | H24: 46113 | K24: 3 | L24: Billable work
A25: Blanka Cindel | B25: =IF(COUNTIF(Team!$A$2:$A$18,A25)>0,"CPS","") | C25: Sonrisa Office Management | D25: Sonrisa | F25: Travel Insurance Management | G25: hó végi lejelentés SRB, MVH travel | H25: 46113 | K25: 0.5 | L25: Non-billable work
A26: Milan Agatonovic | B26: =IF(COUNTIF(Team!$A$2:$A$18,A26)>0,"CPS","") | C26: Consultancy - Observer Service Remap | D26: OBSERVER | E26: 199893 | F26: Regression: The ParlAI hostname from env is not used | H26: 46113 | K26: 0.25 | L26: Billable work
A27: Dániel Kerner | B27: =IF(COUNTIF(Team!$A$2:$A$18,A27)>0,"CPS","") | C27: SAG-NAV | D27: Sagemcom Magyarország Kft. | E27: 200226 | F27: #136519 - ePG- ePénztárgép szoftverfrissítés helyesírási hiba | H27: 46113 | K27: 0.5 | L27: Billable work
A28: Bálint Szente | B28: =IF(COUNTIF(Team!$A$2:$A$18,A28)>0,"CPS","") | C28: KV development | D28: Sonrisa | E28: 199598 | F28: Bug - basic user limitations are not met | G28: exception configs | H28: 46113 | K28: 1 | L28: Non-billable work
A29: Milan Agatonovic | B29: =IF(COUNTIF(Team!$A$2:$A$18,A29)>0,"CPS","") | C29: Consultancy - Observer Service Remap | D29: OBSERVER | E29: 199896 | F29: Read GoogleTranslate settings from env instead of mongodb | H29: 46113 | K29: 0.25 | L29: Billable work
A30: Zoltán Bernátsky | B30: =IF(COUNTIF(Team!$A$2:$A$18,A30)>0,"CPS","") | C30: Diligent BOS sunset | D30: Diligent | E30: 193333 | F30: QA / Testing | H30: 46113 | K30: 8 | L30: Billable work
A31: Levente Gábos | B31: =IF(COUNTIF(Team!$A$2:$A$18,A31)>0,"CPS","") | C31: SocialBudNewJira | D31: SocialBud | E31: 1004592 | F31: SB-4592 - Improve UX with contextual actions for draft posts and generated images | G31: JIRAID:31164 | H31: 46113 | K31: 4.25 | L31: Billable work
A32: Dániel Kerner | B32: =IF(COUNTIF(Team!$A$2:$A$18,A32)>0,"CPS","") | C32: SAG-NAV | D32: Sagemcom Magyarország Kft. | F32: Kódminőség javítás | G32: Teszt üzenetek szűrő bugfix | H32: 46113 | K32: 2 | L32: Billable work
A33: Blanka Cindel | B33: =IF(COUNTIF(Team!$A$2:$A$18,A33)>0,"CPS","") | C33: Sonrisa Office Management | D33: Sonrisa | F33: Site Operation | G33: wc tartály nem működik + óraleolvasások + napi + vízgép szerelővel koordinálás, mert munkaidő után jött | H33: 46113 | K33: 1 | L33: Non-billable work
A34: Milan Agatonovic | B34: =IF(COUNTIF(Team!$A$2:$A$18,A34)>0,"CPS","") | C34: Consultancy - Observer Service Remap | D34: OBSERVER | E34: 199897 | F34: Channel Programmes tab: Table is not rendered correctly on the 1st load | H34: 46113 | K34: 0.5 | L34: Billable work
A35: Bálint Szente | B35: =IF(COUNTIF(Team!$A$2:$A$18,A35)>0,"CPS","") | C35: KV development | D35: Sonrisa | E35: 199576 | F35: Balint KV local rampup | G35: fixing .gitignores and vscode settings.json | H35: 46113 | K35: 1 | L35: Non-billable work
A36: Róbert Benyi | B36: =IF(COUNTIF(Team!$A$2:$A$18,A36)>0,"CPS","") | C36: Diligent Risk Essentials | D36: Diligent | E36: 186319 | F36: Development | H36: 46113 | K36: 8 | L36: Billable work
A37: Milan Agatonovic | B37: =IF(COUNTIF(Team!$A$2:$A$18,A37)>0,"CPS","") | C37: Consultancy - Observer Service Remap | D37: OBSERVER | E37: 199898 | F37: Reindexer reads FRESH_DATA_BOUNDARY from the wrong db | H37: 46113 | K37: 0.25 | L37: Billable work
A38: Sándor-Loránd Nagy | B38: =IF(COUNTIF(Team!$A$2:$A$18,A38)>0,"CPS","") | C38: Boeing 737 | D38: Collinear Group | F38: Project management and administration | G38: Timesheets and administration | H38: 46113 | K38: 2 | L38: Billable work
A39: Gábor Bálint | B39: =IF(COUNTIF(Team!$A$2:$A$18,A39)>0,"CPS","") | C39: Global Blue - Rex - Japan 2026 | D39: Global Blue | F39: Project Management and Administration | H39: 46113 | K39: 2.75 | L39: Billable work
A40: Blanka Cindel | B40: =IF(COUNTIF(Team!$A$2:$A$18,A40)>0,"CPS","") | C40: Sonrisa Office Management | D40: Sonrisa | F40: Asset Management | G40: Vörös Viktor, Tibi | H40: 46113 | K40: 0.5 | L40: Non-billable work
A41: Milan Agatonovic | B41: =IF(COUNTIF(Team!$A$2:$A$18,A41)>0,"CPS","") | C41: Consultancy - Observer Service Remap | D41: OBSERVER | E41: 199899 | F41: Implement configurable lookback time for ES indexer | H41: 46113 | K41: 0.25 | L41: Billable work
A42: Levente Gábos | B42: =IF(COUNTIF(Team!$A$2:$A$18,A42)>0,"CPS","") | C42: SocialBudNewJira | D42: SocialBud | E42: 1003663 | F42: SB-3663 - Meeting participation, meeting preparations, written communication, process updates | G42: JIRAID:31162 DSM | H42: 46113 | K42: 0.25 | L42: Billable work
A43: Blanka Cindel | B43: =IF(COUNTIF(Team!$A$2:$A$18,A43)>0,"CPS","") | C43: Sonrisa Office Management | D43: Sonrisa | F43: ERP Administration | G43: approval hierarchy bug | H43: 46113 | K43: 1.75 | L43: Non-billable work
A44: Predrag Knežević | B44: =IF(COUNTIF(Team!$A$2:$A$18,A44)>0,"CPS","") | C44: Synlab Plasma (BigCommerce) | D44: Synlab | E44: 1019195 | F44: SA-19195 - [IT][eCom][PG] PDP redesign - Drop1 | G44: JIRAID:110756 | H44: 46113 | K44: 1 | L44: Billable work
A45: Milan Agatonovic | B45: =IF(COUNTIF(Team!$A$2:$A$18,A45)>0,"CPS","") | C45: Consultancy - Observer Service Remap | D45: OBSERVER | E45: 199880 | F45: Regression in regex in articleextractor | H45: 46113 | K45: 3 | L45: Billable work
A46: Predrag Knežević | B46: =IF(COUNTIF(Team!$A$2:$A$18,A46)>0,"CPS","") | C46: Synlab Plasma (BigCommerce) | D46: Synlab | E46: 1019195 | F46: SA-19195 - [IT][eCom][PG] PDP redesign - Drop1 | G46: JIRAID:110758 | H46: 46113 | K46: 6.75 | L46: Billable work
A47: Milan Agatonovic | B47: =IF(COUNTIF(Team!$A$2:$A$18,A47)>0,"CPS","") | C47: Consultancy - Observer Service Remap | D47: OBSERVER | E47: 199853 | F47: Reindexer Improvements | H47: 46113 | K47: 3 | L47: Billable work
A48: Domos Kresz | B48: =IF(COUNTIF(Team!$A$2:$A$18,A48)>0,"CPS","") | C48: Idomsoft - Legacy költöztetés | D48: IdomSoft Zrt. | F48: Megbeszélés | H48: 46113 | K48: 0.5 | L48: Billable work
A49: Pál Milán Domanovszki | B49: =IF(COUNTIF(Team!$A$2:$A$18,A49)>0,"CPS","") | C49: Synlab Plasma (BigCommerce) | D49: Synlab | E49: 1019192 | F49: SA-19192 - [IT] Website & webshop template solution Release 3 | G49: JIRAID:110769 Creating IT SEO tickets | H49: 46113 | K49: 1 | L49: Billable work
A50: Milan Agatonovic | B50: =IF(COUNTIF(Team!$A$2:$A$18,A50)>0,"CPS","") | C50: Consultancy - Observer Service Remap | D50: OBSERVER | E50: 199651 | F50: Meetings | H50: 46113 | K50: 1.5 | L50: Billable work
A51: Domos Kresz | B51: =IF(COUNTIF(Team!$A$2:$A$18,A51)>0,"CPS","") | C51: Idomsoft - Legacy költöztetés | D51: IdomSoft Zrt. | F51: Development | H51: 46113 | K51: 7.5 | L51: Billable work
A52: Gergely Bódi | B52: =IF(COUNTIF(Team!$A$2:$A$18,A52)>0,"CPS","") | C52: Silver 3.0 | D52: Spinwheel | E52: 1000468 | F52: SIL-468 - Define persona template schema and storage | G52: JIRAID:16720 review | H52: 46113 | K52: 0.5 | L52: Billable work
A53: Blanka Cindel | B53: =IF(COUNTIF(Team!$A$2:$A$18,A53)>0,"CPS","") | C53: Sonrisa Office Management | D53: Sonrisa | F53: Administrative Help | G53: Ognjen | H53: 46113 | K53: 0.25 | L53: Non-billable work
A54: Szabolcs Siko | B54: =IF(COUNTIF(Team!$A$2:$A$18,A54)>0,"CPS","") | C54: Synlab Plasma (BigCommerce) | D54: Synlab | E54: 1019158 | F54: SA-19158 - [IT][eCom][PG] Category main page 2 - Visite specialistiche e diagnotica per immagini - D | G54: JIRAID:110766 | H54: 46113 | K54: 4 | L54: Billable work
A55: Andor Zöldesi | B55: =IF(COUNTIF(Team!$A$2:$A$18,A55)>0,"CPS","") | C55: Diligent Risk Essentials | D55: Diligent | E55: 186321 | F55: TL work | H55: 46113 | K55: 5 | L55: Billable work
A56: László Vékony | B56: =IF(COUNTIF(Team!$A$2:$A$18,A56)>0,"CPS","") | C56: Other | D56: Sonrisa | F56: Paid leave | H56: 46113 | K56: 8 | L56: Non-work activity
A57: Dániel Fazekas | B57: =IF(COUNTIF(Team!$A$2:$A$18,A57)>0,"CPS","") | C57: Yettel - GRIP | D57: Yettel | F57: Yettel - Grip - Internal Meeting | H57: 46113 | K57: 2.5 | L57: Billable work
A58: Szabolcs Siko | B58: =IF(COUNTIF(Team!$A$2:$A$18,A58)>0,"CPS","") | C58: Synlab Plasma (BigCommerce) | D58: Synlab | E58: 1018967 | F58: SA-18967 - [IT][Booking] Product details page during checkout when user clicks "scopri di piu" | G58: JIRAID:110765 | H58: 46113 | K58: 3.5 | L58: Billable work
A59: Milan Agatonovic | B59: =IF(COUNTIF(Team!$A$2:$A$18,A59)>0,"CPS","") | C59: Consultancy - Observer Service Remap | D59: OBSERVER | E59: 199603 | F59: UAT - Company - Cutting loading raw material load error | H59: 46113 | K59: 2 | L59: Billable work
A60: Dániel Fazekas | B60: =IF(COUNTIF(Team!$A$2:$A$18,A60)>0,"CPS","") | C60: Yettel - GRIP | D60: Yettel | F60: Yettel - Grip - Internal Meeting | H60: 46113 | K60: 0.5 | L60: Billable work
A61: Judit Franciska Hegedűs | B61: =IF(COUNTIF(Team!$A$2:$A$18,A61)>0,"CPS","") | C61: UI modernization 2026 - UX_BA_Team | D61: Diligent | F61: Meeting | G61: dev DSM, reminders meeting, canReadOverride meeting with Viktor Faddi | H61: 46113 | K61: 1 | L61: Billable work
A62: Gábor Bálint | B62: =IF(COUNTIF(Team!$A$2:$A$18,A62)>0,"CPS","") | C62: SAG-NAV | D62: Sagemcom Magyarország Kft. | F62: DSM, Meetings | H62: 46113 | K62: 0.5 | L62: Billable work
A63: Mihály-Attila Nánási | B63: =IF(COUNTIF(Team!$A$2:$A$18,A63)>0,"CPS","") | C63: UI modernization 2026 - Dev Team | D63: Diligent | F63: Meeting | H63: 46113 | K63: 0.25 | L63: Billable work
A64: Péter Varga | B64: =IF(COUNTIF(Team!$A$2:$A$18,A64)>0,"CPS","") | C64: Resource management | D64: Sonrisa | E64: 115085 | F64: Resource management | H64: 46113 | K64: 2.5 | L64: Non-billable work
A65: Dániel Fazekas | B65: =IF(COUNTIF(Team!$A$2:$A$18,A65)>0,"CPS","") | C65: Yettel - GRIP | D65: Yettel | F65: Yettel - Grip - Internal Meeting | H65: 46113 | K65: 1 | L65: Billable work
A66: Pál Milán Domanovszki | B66: =IF(COUNTIF(Team!$A$2:$A$18,A66)>0,"CPS","") | C66: Synlab Plasma (BigCommerce) | D66: Synlab | E66: 1018731 | F66: SA-18731 - [IT] Italy Release 3 non-website | G66: JIRAID:110767 Booking flow testing | H66: 46113 | K66: 1 | L66: Billable work
A67: Péter Brindzik | B67: =IF(COUNTIF(Team!$A$2:$A$18,A67)>0,"CPS","") | C67: Synlab SDN | D67: Synlab | E67: 1003076 | F67: SDN-3076 - SA: Exceptional case for quiz panels | G67: JIRAID:111310 | H67: 46113 | K67: 0.5 | L67: Billable work
A68: István Balogh | B68: =IF(COUNTIF(Team!$A$2:$A$18,A68)>0,"CPS","") | C68: Waberers-Continuity | D68: WABERER’S INTERNATIONAL Nyrt. | E68: 448 | F68: [407237] RPA - Igény Ziktat3 számlakép lekérdezések | H68: 46113 | K68: 2 | L68: Billable work
A69: Krisztián Tombácz | B69: =IF(COUNTIF(Team!$A$2:$A$18,A69)>0,"CPS","") | C69: Diligent - Boards - Hydra | D69: Diligent | F69: Development | G69: BCLOUD-9834 | H69: 46113 | K69: 8 | L69: Billable work
A70: Dániel Fazekas | B70: =IF(COUNTIF(Team!$A$2:$A$18,A70)>0,"CPS","") | C70: Yettel - GRIP | D70: Yettel | F70: Testing | H70: 46113 | K70: 4 | L70: Billable work
A71: Pál Milán Domanovszki | B71: =IF(COUNTIF(Team!$A$2:$A$18,A71)>0,"CPS","") | C71: Synlab Plasma (BigCommerce) | D71: Synlab | E71: 1018731 | F71: SA-18731 - [IT] Italy Release 3 non-website | G71: JIRAID:110771 IT booking workflow testing, Meeting with Daniel about IT order status / refund handling, Italy June Release (demo), clarification with Mark about the booking dashboard page redesign, checking redesign mocks. | H71: 46113 | K71: 6 | L71: Billable work
A72: Bence Farkas | B72: =IF(COUNTIF(Team!$A$2:$A$18,A72)>0,"CPS","") | C72: Lufthansa-Continuity | D72: Lufthansa | E72: 199451 | F72: DCS_html mysql upgrade után a php projektek elhasaltak | H72: 46113 | K72: 2 | L72: Billable work
A73: István Balogh | B73: =IF(COUNTIF(Team!$A$2:$A$18,A73)>0,"CPS","") | C73: Waberers-Continuity | D73: WABERER’S INTERNATIONAL Nyrt. | E73: 447 | F73: Brexit {FOID} azonosítójú járat nincs kiküldve az iCMR-re! esetén nem küldünk emailt | H73: 46113 | K73: 3 | L73: Billable work
A74: Andor Szabó | B74: =IF(COUNTIF(Team!$A$2:$A$18,A74)>0,"CPS","") | C74: Cloud Platform Services | D74: Sonrisa | E74: 196631 | F74: Diligent - ARC BOS Sunset | H74: 46113 | K74: 8 | L74: Billable work
A75: Judit Franciska Hegedűs | B75: =IF(COUNTIF(Team!$A$2:$A$18,A75)>0,"CPS","") | C75: UI modernization 2026 - UX_BA_Team | D75: Diligent | F75: BA activity | G75: Q1 cleanup, even testing bug to close an epic, consider the override everywhere when assignedTo read is restricted, product review of GSV tickets, inline edit system field collection | H75: 46113 | K75: 8.25 | L75: Billable work
A76: Gábor Bálint | B76: =IF(COUNTIF(Team!$A$2:$A$18,A76)>0,"CPS","") | C76: SAG-NTAK | D76: Sagemcom Magyarország Kft. | E76: 123179 | F76: #28997 Workshop - NTAK DSM - Sonrisa | H76: 46113 | K76: 0.5 | L76: Billable work
A77: Péter Brindzik | B77: =IF(COUNTIF(Team!$A$2:$A$18,A77)>0,"CPS","") | C77: Synlab SDN | D77: Synlab | E77: 1003045 | F77: SDN-3045 - [SDN] Meetings (Planning, DSM, retro, demo, ad-hoc) | G77: JIRAID:111312 tech-discussion | H77: 46113 | K77: 1 | L77: Billable work
A78: Roland Lamoli | B78: =IF(COUNTIF(Team!$A$2:$A$18,A78)>0,"CPS","") | C78: Other | D78: Sonrisa | F78: Waiting for assignment | H78: 46113 | K78: 8 | L78: Non-billable work
A79: István Balogh | B79: =IF(COUNTIF(Team!$A$2:$A$18,A79)>0,"CPS","") | C79: Waberers-Continuity | D79: WABERER’S INTERNATIONAL Nyrt. | E79: 438 | F79: Brexit ELO bizonyos esetekben nem kerül küldésre | H79: 46113 | K79: 3 | L79: Billable work
A80: Balázs Schéder | B80: =IF(COUNTIF(Team!$A$2:$A$18,A80)>0,"CPS","") | C80: KV development | D80: Sonrisa | E80: 199537 | F80: [BE] Refactor: Reduce Mixed Sync/Async Usage and Align with Best Practices | H80: 46113 | K80: 8 | L80: Non-billable work
A81: Patrik Fábián | B81: =IF(COUNTIF(Team!$A$2:$A$18,A81)>0,"CPS","") | C81: Talentedbunch | D81: Talented Bunch Zrt. | F81: Meetings | H81: 46113 | K81: 0.75 | L81: Billable work
A82: László Szegedi | B82: =IF(COUNTIF(Team!$A$2:$A$18,A82)>0,"CPS","") | C82: Other | D82: Sonrisa | F82: Waiting for assignment | H82: 46113 | K82: 8 | L82: Non-billable work
A83: Bence Farkas | B83: =IF(COUNTIF(Team!$A$2:$A$18,A83)>0,"CPS","") | C83: Lufthansa-Continuity | D83: Lufthansa | E83: 199156 | F83: LCAGCABS31 - MariaDB: End of Life | H83: 46113 | K83: 6 | L83: Billable work
A84: Kinga Zelei | B84: =IF(COUNTIF(Team!$A$2:$A$18,A84)>0,"CPS","") | C84: Consultancy - Observer Service Remap | D84: OBSERVER | E84: 199876 | F84: UAT - Company - ChatGPT operations icon is missing on Newsclip executive summary page | H84: 46113 | K84: 1 | L84: Billable work
A85: Gábor Bálint | B85: =IF(COUNTIF(Team!$A$2:$A$18,A85)>0,"CPS","") | C85: SAG-NTAK | D85: Sagemcom Magyarország Kft. | E85: 123178 | F85: #28996 Workshop - NTAK DSM - Sagemcom | H85: 46113 | K85: 0.5 | L85: Billable work
A86: Péter Brindzik | B86: =IF(COUNTIF(Team!$A$2:$A$18,A86)>0,"CPS","") | C86: Synlab SDN | D86: Synlab | E86: 1003014 | F86: SDN-3014 - EE: SAP Integration | G86: JIRAID:111311 | H86: 46113 | K86: 0.5 | L86: Billable work
A87: Bálint Nagy | B87: =IF(COUNTIF(Team!$A$2:$A$18,A87)>0,"CPS","") | C87: Global Blue - Rex - Japan 2026 | D87: Global Blue | F87: Japan Refunding | H87: 46113 | K87: 8 | L87: Billable work
A88: Éva-Henrietta Nagy | B88: =IF(COUNTIF(Team!$A$2:$A$18,A88)>0,"CPS","") | C88: K11 Support | D88: Magyar Államkincstár | E88: 197621 | F88: Adatszolgáltatási Nyilvántartás rendszer (ASZNY) fejlesztésére vonatkozó becslés | G88: folytatás + excel összegző + csúsztatás | H88: 46113 | K88: 4 | L88: Billable work
A89: Kinga Zelei | B89: =IF(COUNTIF(Team!$A$2:$A$18,A89)>0,"CPS","") | C89: Consultancy - Observer Service Remap | D89: OBSERVER | E89: 199877 | F89: UAT - Shared - Domains throw gateway timeout when I open for editing | H89: 46113 | K89: 0.5 | L89: Billable work
A90: Tamás János Szalai | B90: =IF(COUNTIF(Team!$A$2:$A$18,A90)>0,"CPS","") | C90: Silver 3.0 | D90: Spinwheel | E90: 1000340 | F90: SIL-340 - STT Select Candidate: candidate results grid and user selection state | G90: JIRAID:18022 | H90: 46113 | K90: 6 | L90: Billable work
A91: Kinga Zelei | B91: =IF(COUNTIF(Team!$A$2:$A$18,A91)>0,"CPS","") | C91: Consultancy - Observer Service Remap | D91: OBSERVER | E91: 199878 | F91: UAT - Shared - RSS monitoring is not downloading automatically | H91: 46113 | K91: 0.5 | L91: Billable work
A92: Gábor Bálint | B92: =IF(COUNTIF(Team!$A$2:$A$18,A92)>0,"CPS","") | C92: GlobalBlue - 2026 PDF Invoicing | D92: Global Blue | F92: Project Management and Administration | H92: 46113 | K92: 0.75 | L92: Billable work
A93: Tamás Kinsztler | B93: =IF(COUNTIF(Team!$A$2:$A$18,A93)>0,"CPS","") | C93: K11 Production | D93: Magyar Államkincstár | E93: 199716 | F93: Intézmény adatok megjelenitése | H93: 46113 | K93: 8 | L93: Billable work
A94: Kinga Zelei | B94: =IF(COUNTIF(Team!$A$2:$A$18,A94)>0,"CPS","") | C94: Consultancy - Observer Service Remap | D94: OBSERVER | E94: 199879 | F94: UAT - Shared - Not RSS load page is not working | H94: 46113 | K94: 0.5 | L94: Billable work
A95: Gábor Bálint | B95: =IF(COUNTIF(Team!$A$2:$A$18,A95)>0,"CPS","") | C95: Global Blue - Layout Invoicing | D95: Global Blue | E95: 1 | F95: Project Management and Administration | H95: 46113 | K95: 1 | L95: Billable work
A96: Balázs Papp | B96: =IF(COUNTIF(Team!$A$2:$A$18,A96)>0,"CPS","") | C96: Silver 3.0 | D96: Spinwheel | E96: 1000571 | F96: SIL-571 - Code review | G96: JIRAID:18130 | H96: 46113 | K96: 3 | L96: Billable work
A97: Péter Szekeres | B97: =IF(COUNTIF(Team!$A$2:$A$18,A97)>0,"CPS","") | C97: Synlab HU | D97: Synlab | F97: BE development | H97: 46113 | K97: 8 | L97: Billable work
A98: Bálint Szente | B98: =IF(COUNTIF(Team!$A$2:$A$18,A98)>0,"CPS","") | C98: KV development | D98: Sonrisa | E98: 199598 | F98: Bug - basic user limitations are not met | G98: searching for cause | H98: 46113 | K98: 1 | L98: Non-billable work
A99: Csaba Kun | B99: =IF(COUNTIF(Team!$A$2:$A$18,A99)>0,"CPS","") | C99: Boeing 737 | D99: Collinear Group | F99: General Development | H99: 46113 | K99: 8 | L99: Billable work
A100: Kinga Zelei | B100: =IF(COUNTIF(Team!$A$2:$A$18,A100)>0,"CPS","") | C100: Consultancy - Observer Service Remap | D100: OBSERVER | E100: 199585 | F100: QA task for UAT | H100: 46113 | K100: 2.5 | L100: Billable work
A101: Predrag Knežević | B101: =IF(COUNTIF(Team!$A$2:$A$18,A101)>0,"CPS","") | C101: Synlab Plasma (BigCommerce) | D101: Synlab | E101: 1015152 | F101: SA-15152 - [OE] Scrum meetings (planning, DSM, retro, demo) | G101: JIRAID:110757 | H101: 46113 | K101: 0.25 | L101: Billable work
A102: István Dénes | B102: =IF(COUNTIF(Team!$A$2:$A$18,A102)>0,"CPS","") | C102: Synlab Plasma (BigCommerce) | D102: Synlab | E102: 1018731 | F102: SA-18731 - [IT] Italy Release 3 non-website | G102: JIRAID:110909 Sprint 93 ticket estimation | H102: 46113 | K102: 2.5 | L102: Billable work
...

Sheet CPS
A1: User | B1: Team | C1: Project name | D1: Company name | E1: Task issue ID | F1: Task name | G1: Activity description | H1: Activity date | I1: Start time | J1: End time | K1: Length | L1: Work type
A2: Marcell Kovács | B2: CPS | C2: Cloud Platform Services | D2: Sonrisa | E2: 193502 | F2: ColosseumDental | H2: 46113 | K2: 4 | L2: Billable work
A3: Marcell Kovács | B3: CPS | C3: Synlab Plasma (BigCommerce) | D3: Synlab | E3: 8000751 | F3: SD-751 - Create a MongoDB View that can provide BI Team results data requirement | G3: JIRAID:110749 | H3: 46113 | K3: 2.5 | L3: Billable work
A4: Bálint Lajos Török | B4: CPS | C4: Cloud Platform Services | D4: Sonrisa | E4: 197976 | F4: IdomSoft - Faker Microsite Platform | G4: nkfh, VM hozzaferes ellenorzese, piler sync | H4: 46113 | K4: 2 | L4: Billable work
A5: Attila Kovács | B5: CPS | C5: Jumio AWS | D5: Jumio | E5: 181325 | F5: Development and operations | H5: 46113 | K5: 8 | L5: Billable work
A6: Bálint Lajos Török | B6: CPS | C6: Cloud Platform Services | D6: Sonrisa | E6: 196631 | F6: Diligent - ARC BOS Sunset | G6: cmmc bug fixes, | H6: 46113 | K6: 6 | L6: Billable work
A7: István Bánfi | B7: CPS | C7: Consultancy - Observer Service Remap | D7: OBSERVER | E7: 199805 | F7: 3.6.ParlAI API bekötése - UAT | H7: 46113 | K7: 2 | L7: Billable work
A8: Bálint Lajos Török | B8: CPS | C8: CPS Support | D8: Sonrisa | E8: 195325 | F8: MVMI OMNI - general availability collector ticket | H8: 46113 | K8: 6 | L8: Billable work
A9: Andor Szabó | B9: CPS | C9: Cloud Platform Services | D9: Sonrisa | E9: 196631 | F9: Diligent - ARC BOS Sunset | H9: 46113 | K9: 8 | L9: Billable work
A10: István Bánfi | B10: CPS | C10: Idomsoft - Legacy költöztetés | D10: IdomSoft Zrt. | F10: Megbeszélés | H10: 46113 | K10: 2 | L10: Billable work
A11: István Bánfi | B11: CPS | C11: Silver 3.0 | D11: Spinwheel | E11: 1000570 | F11: SIL-570 - Configure CD for deploying freeswitch | H11: 46113 | K11: 1 | L11: Billable work
A12: István Bánfi | B12: CPS | C12: Silver 3.0 | D12: Spinwheel | E12: 1000492 | F12: SIL-492 - SCM: Whisper setup | H12: 46113 | K12: 3 | L12: Billable work
A13: Zsolt Tornai | B13: CPS | C13: NKP-MTR | D13: NKP | E13: 198388 | F13: [SUPPORT] NKP MTR Rendszerek állapotának ellenőrzése - 2026.01.01 - 2026.12.31 közötti időszakban | H13: 46113 | K13: 2 | L13: Billable work
A14: Márk-Ádám Vaida | B14: CPS | C14: Cloud Platform Services | D14: Sonrisa | E14: 189341 | F14: MVMI | G14: Meeting - ONEDC - CI/CD státusz | H14: 46113 | K14: 0.5 | L14: Billable work
A15: Márk-Ádám Vaida | B15: CPS | C15: Cloud Platform Services | D15: Sonrisa | E15: 194703 | F15: Aws Inference Farm | G15: 199861 - Need Decision - Monitoring stack / Langfuse integration | H15: 46113 | K15: 2.5 | L15: Billable work
A16: Márk-Ádám Vaida | B16: CPS | C16: Cloud Platform Services | D16: Sonrisa | E16: 194703 | F16: Aws Inference Farm | G16: 199854 - CleanUp Model Tags from Openwebui | H16: 46113 | K16: 0.25 | L16: Billable work
A17: Márk-Ádám Vaida | B17: CPS | C17: Cloud Platform Services | D17: Sonrisa | E17: 194703 | F17: Aws Inference Farm | G17: 199772 - FutureProof Monitoring | H17: 46113 | K17: 4.75 | L17: Billable work
A18: Zsolt Tornai | B18: CPS | C18: Synlab Plasma (BigCommerce) | D18: Synlab | E18: 8000748 | F18: SD-748 - Azure VPN Gateway SKU Upgrade | G18: JIRAID:113267 | H18: 46113 | K18: 6 | L18: Billable work
A19: Dániel Molnár | B19: CPS | C19: Synlab Plasma (BigCommerce) | D19: Synlab | E19: 8000748 | F19: SD-748 - Azure VPN Gateway SKU Upgrade | G19: JIRAID:113468 | H19: 46113 | K19: 1 | L19: Billable work
A20: Zoltán Szántó | B20: CPS | C20: Cloud Platform Services | D20: Sonrisa | E20: 186697 | F20: Bayer | H20: 46113 | K20: 8 | L20: Billable work
A21: Botond Gáll | B21: CPS | C21: Cloud Platform Services | D21: Sonrisa | E21: 196190 | F21: DirectTravel | G21: qa and prod env | H21: 46113 | K21: 4 | L21: Billable work
A22: Botond Gáll | B22: CPS | C22: Cloud Platform Services | D22: Sonrisa | E22: 193502 | F22: ColosseumDental | G22: Azure tananyag összeállítás | H22: 46113 | K22: 2 | L22: Billable work
A23: Botond Gáll | B23: CPS | C23: Cloud Platform Services | D23: Sonrisa | E23: 190306 | F23: Sontools | G23: logic apps, sonplan mock backend | H23: 46113 | K23: 2 | L23: Billable work
A24: Dániel Molnár | B24: CPS | C24: Cloud Platform Services | D24: Sonrisa | E24: 196190 | F24: DirectTravel | H24: 46113 | K24: 2 | L24: Billable work
A25: Dániel Molnár | B25: CPS | C25: Cloud Platform Services | D25: Sonrisa | E25: 186698 | F25: greeHill | H25: 46113 | K25: 1 | L25: Billable work
A26: Dániel Molnár | B26: CPS | C26: Cloud Platform Services | D26: Sonrisa | E26: 187810 | F26: Meeting | H26: 46113 | K26: 2 | L26: Non-billable work
A27: Dániel Molnár | B27: CPS | C27: Cloud Platform Services | D27: Sonrisa | E27: 193251 | F27: General Research | H27: 46113 | K27: 2 | L27: Billable work
A28: Marcell Kovács | B28: CPS | C28: Cloud Platform Services | D28: Sonrisa | E28: 193502 | F28: ColosseumDental | H28: 46113 | K28: 1.5 | L28: Billable work
A29: Ferenc Beder | B29: CPS | C29: Lufthansa Netline - Crew | D29: Lufthansa | F29: General development | H29: 46113 | K29: 8 | L29: Billable work
A30: Alexandru Ceclan | B30: CPS | C30: Consultancy - Observer Service Remap | D30: OBSERVER | E30: 199612 | F30: 1.6 ES index inicializálás (template) - ES index inicialisation | H30: 46113 | K30: 2 | L30: Billable work
A31: Alexandru Ceclan | B31: CPS | C31: Consultancy - Observer Service Remap | D31: OBSERVER | E31: 199314 | F31: 5.1 ES index feltöltés: Generate Indexes from MongoDB | H31: 46113 | K31: 4 | L31: Billable work
A32: Alexander Póda | B32: CPS | C32: Cloud Platform Services | D32: Sonrisa | E32: 195562 | F32: Observer | G32: sftp-newscliparchive, meetings, | H32: 46113 | K32: 8 | L32: Billable work
A33: Dávid Pap | B33: CPS | C33: Cloud Platform Services | D33: Sonrisa | E33: 196631 | F33: Diligent - ARC BOS Sunset | H33: 46113 | I33: 46113.333 | J33: 46113.667 | K33: 8 | L33: Billable work
A34: Dávid Pap | B34: CPS | C34: CPS Support | D34: Sonrisa | E34: 195325 | F34: MVMI OMNI - general availability collector ticket | H34: 46113 | I34: 46113.917 | J34: 46114 | K34: 2 | L34: Billable work
A35: Marcell Kovács | B35: CPS | C35: Cloud Platform Services | D35: Sonrisa | E35: 193502 | F35: ColosseumDental | H35: 46114 | K35: 8 | L35: Billable work
A36: Bálint Lajos Török | B36: CPS | C36: Cloud Platform Services | D36: Sonrisa | E36: 187810 | F36: Meeting | G36: cps sync | H36: 46114 | K36: 0.5 | L36: Non-billable work
A37: Bálint Lajos Török | B37: CPS | C37: Cloud Platform Services | D37: Sonrisa | E37: 196631 | F37: Diligent - ARC BOS Sunset | G37: test writing for old cisco, Poda Sanyival last few weeks sync meeting | H37: 46114 | K37: 5.5 | L37: Billable work
A38: Andor Szabó | B38: CPS | C38: Cloud Platform Services | D38: Sonrisa | E38: 196631 | F38: Diligent - ARC BOS Sunset | H38: 46114 | K38: 8 | L38: Billable work
A39: Bálint Lajos Török | B39: CPS | C39: Cloud Platform Services | D39: Sonrisa | E39: 189987 | F39: Learning | G39: python test for diligent | H39: 46114 | K39: 2 | L39: Billable work
A40: Attila Kovács | B40: CPS | C40: Jumio AWS | D40: Jumio | E40: 181325 | F40: Development and operations | H40: 46114 | K40: 8 | L40: Billable work
A41: Alexander Póda | B41: CPS | C41: Cloud Platform Services | D41: Sonrisa | E41: 196631 | F41: Diligent - ARC BOS Sunset | G41: CIco robot test | H41: 46114 | K41: 8 | L41: Billable work
A42: Márk-Ádám Vaida | B42: CPS | C42: Cloud Platform Services | D42: Sonrisa | E42: 189341 | F42: MVMI | G42: MVMI CI/CD | H42: 46114 | K42: 0.5 | L42: Billable work
A43: Márk-Ádám Vaida | B43: CPS | C43: Cloud Platform Services | D43: Sonrisa | E43: 187810 | F43: Meeting | G43: Cloud Platform Services - Weekly sync | H43: 46114 | K43: 0.5 | L43: Non-billable work
A44: Márk-Ádám Vaida | B44: CPS | C44: Cloud Platform Services | D44: Sonrisa | E44: 187810 | F44: Meeting | G44: Growth framework AI updates | H44: 46114 | K44: 0.5 | L44: Non-billable work
A45: Márk-Ádám Vaida | B45: CPS | C45: Cloud Platform Services | D45: Sonrisa | E45: 189988 | F45: Onriva: Availability, Monitoring, Meetings | G45: Cost optimization report | H45: 46114 | K45: 0.25 | L45: Billable work
A46: Márk-Ádám Vaida | B46: CPS | C46: Cloud Platform Services | D46: Sonrisa | E46: 194703 | F46: Aws Inference Farm | G46: 199772 - FutureProof Monitoring | H46: 46114 | K46: 1.25 | L46: Billable work
A47: Dávid Pap | B47: CPS | C47: CPS Support | D47: Sonrisa | E47: 195325 | F47: MVMI OMNI - general availability collector ticket | H47: 46114 | I47: 46114 | J47: 46114.333 | K47: 8 | L47: Billable work
A48: Márk-Ádám Vaida | B48: CPS | C48: CPS Support | D48: Sonrisa | E48: 195325 | F48: MVMI OMNI - general availability collector ticket | G48: 2026.04.03 | H48: 46114 | K48: 8 | L48: Billable work
A49: Zsolt Tornai | B49: CPS | C49: Synlab Plasma (BigCommerce) | D49: Synlab | E49: 8000748 | F49: SD-748 - Azure VPN Gateway SKU Upgrade | G49: JIRAID:113268 | H49: 46114 | K49: 8 | L49: Billable work
A50: Zoltán Szántó | B50: CPS | C50: Cloud Platform Services | D50: Sonrisa | E50: 186697 | F50: Bayer | H50: 46114 | K50: 8 | L50: Billable work
A51: Márk-Ádám Vaida | B51: CPS | C51: Cloud Platform Services | D51: Sonrisa | E51: 189988 | F51: Onriva: Availability, Monitoring, Meetings | G51: TECHOPS-5596 || Travel Marketplace Release v243 | H51: 46114 | K51: 5 | L51: Billable work
A52: Botond Gáll | B52: CPS | C52: CPS Support | D52: Sonrisa | E52: 195325 | F52: MVMI OMNI - general availability collector ticket | H52: 46114 | K52: 6 | L52: Billable work
A53: Zoltán Szántó | B53: CPS | C53: CPS Support | D53: Sonrisa | E53: 195325 | F53: MVMI OMNI - general availability collector ticket | H53: 46114 | K53: 10 | L53: Billable work
A54: Botond Gáll | B54: CPS | C54: Cloud Platform Services | D54: Sonrisa | E54: 193502 | F54: ColosseumDental | G54: Azure tanulóanyag Bencének | H54: 46114 | K54: 3 | L54: Billable work
A55: Botond Gáll | B55: CPS | C55: Cloud Platform Services | D55: Sonrisa | E55: 196190 | F55: DirectTravel | G55: qa and prod fixes | H55: 46114 | K55: 3 | L55: Billable work
A56: Botond Gáll | B56: CPS | C56: Cloud Platform Services | D56: Sonrisa | E56: 190306 | F56: Sontools | G56: mock backend with azure logic apps | H56: 46114 | K56: 2 | L56: Billable work
A57: Dániel Molnár | B57: CPS | C57: Cloud Platform Services | D57: Sonrisa | E57: 187810 | F57: Meeting | H57: 46114 | K57: 3 | L57: Non-billable work
A58: Botond Gáll | B58: CPS | C58: Cloud Platform Services | D58: Sonrisa | E58: 187810 | F58: Meeting | G58: Cloud Platform Services - Weekly sync | H58: 46114 | K58: 0.5 | L58: Non-billable work
A59: Dániel Molnár | B59: CPS | C59: Cloud Platform Services | D59: Sonrisa | E59: 186698 | F59: greeHill | H59: 46114 | K59: 2 | L59: Billable work
A60: István Bánfi | B60: CPS | C60: Idomsoft - Legacy költöztetés | D60: IdomSoft Zrt. | F60: Megbeszélés | H60: 46114 | K60: 1 | L60: Billable work
A61: Dániel Molnár | B61: CPS | C61: Cloud Platform Services | D61: Sonrisa | E61: 193251 | F61: General Research | H61: 46114 | K61: 2 | L61: Billable work
A62: István Bánfi | B62: CPS | C62: Sonrisa Onboarding | D62: Sonrisa | E62: 2 | F62: Prezentáció | G62: ITO | H62: 46114 | K62: 1 | L62: Non-billable work
A63: Ferenc Beder | B63: CPS | C63: Lufthansa Netline - Crew | D63: Lufthansa | F63: General development | H63: 46114 | K63: 8 | L63: Billable work
A64: István Bánfi | B64: CPS | C64: Idomsoft - Legacy költöztetés | D64: IdomSoft Zrt. | F64: Megbeszélés | H64: 46114 | K64: 2 | L64: Billable work
A65: Dániel Molnár | B65: CPS | C65: Cloud Platform Services | D65: Sonrisa | E65: 196190 | F65: DirectTravel | H65: 46114 | K65: 1 | L65: Billable work
A66: István Bánfi | B66: CPS | C66: Silver 3.0 | D66: Spinwheel | E66: 1000404 | F66: SIL-404 - Setup freeswitch in k8s | H66: 46114 | K66: 4 | L66: Billable work
A67: Alexandru Ceclan | B67: CPS | C67: Cloud Platform Services | D67: Sonrisa | E67: 194703 | F67: Aws Inference Farm | H67: 46114 | K67: 4 | L67: Billable work
A68: Alexandru Ceclan | B68: CPS | C68: Cloud Platform Services | D68: Sonrisa | E68: 187810 | F68: Meeting | H68: 46114 | K68: 1 | L68: Non-billable work
A69: Alexandru Ceclan | B69: CPS | C69: Cloud Platform Services | D69: Sonrisa | E69: 193251 | F69: General Research | H69: 46114 | K69: 1 | L69: Billable work
A70: Dávid Pap | B70: CPS | C70: Cloud Platform Services | D70: Sonrisa | E70: 196631 | F70: Diligent - ARC BOS Sunset | H70: 46114 | I70: 46114.333 | J70: 46114.667 | K70: 8 | L70: Billable work
A71: Bálint Lajos Török | B71: CPS | C71: CPS Support | D71: Sonrisa | E71: 195325 | F71: MVMI OMNI - general availability collector ticket | H71: 46115 | K71: 6 | L71: Billable work
A72: Dávid Pap | B72: CPS | C72: CPS Support | D72: Sonrisa | E72: 195325 | F72: MVMI OMNI - general availability collector ticket | H72: 46115 | I72: 46115.917 | J72: 46116 | K72: 2 | L72: Billable work
A73: Dávid Pap | B73: CPS | C73: CPS Support | D73: Sonrisa | E73: 195325 | F73: MVMI OMNI - general availability collector ticket | H73: 46116 | I73: 46116 | J73: 46116.25 | K73: 6 | L73: Billable work
A74: Márk-Ádám Vaida | B74: CPS | C74: CPS Support | D74: Sonrisa | E74: 195325 | F74: MVMI OMNI - general availability collector ticket | H74: 46116 | K74: 8 | L74: Billable work
A75: Márk-Ádám Vaida | B75: CPS | C75: CPS Support | D75: Sonrisa | E75: 195325 | F75: MVMI OMNI - general availability collector ticket | G75: 2026.04.06 | H75: 46116 | K75: 8 | L75: Billable work
A76: Botond Gáll | B76: CPS | C76: CPS Support | D76: Sonrisa | E76: 195325 | F76: MVMI OMNI - general availability collector ticket | H76: 46116 | K76: 8 | L76: Billable work
A77: Zoltán Szántó | B77: CPS | C77: CPS Support | D77: Sonrisa | E77: 195325 | F77: MVMI OMNI - general availability collector ticket | H77: 46116 | K77: 8 | L77: Billable work
A78: Zoltán Szántó | B78: CPS | C78: CPS Support | D78: Sonrisa | E78: 195325 | F78: MVMI OMNI - general availability collector ticket | H78: 46117 | K78: 10 | L78: Billable work
A79: Dávid Pap | B79: CPS | C79: CPS Support | D79: Sonrisa | E79: 195325 | F79: MVMI OMNI - general availability collector ticket | H79: 46117 | I79: 46117.25 | J79: 46117.583 | K79: 8 | L79: Billable work
A80: Botond Gáll | B80: CPS | C80: CPS Support | D80: Sonrisa | E80: 195325 | F80: MVMI OMNI - general availability collector ticket | H80: 46118 | K80: 10 | L80: Billable work
A81: Dávid Pap | B81: CPS | C81: CPS Support | D81: Sonrisa | E81: 195325 | F81: MVMI OMNI - general availability collector ticket | H81: 46118 | I81: 46118.667 | J81: 46118.917 | K81: 6 | L81: Billable work
A82: Andor Szabó | B82: CPS | C82: Cloud Platform Services | D82: Sonrisa | E82: 196631 | F82: Diligent - ARC BOS Sunset | H82: 46119 | K82: 8 | L82: Billable work
A83: Bálint Lajos Török | B83: CPS | C83: Cloud Platform Services | D83: Sonrisa | E83: 196631 | F83: Diligent - ARC BOS Sunset | G83: cisco test wrinting before refactor | H83: 46119 | K83: 6 | L83: Billable work
A84: Bálint Lajos Török | B84: CPS | C84: Cloud Platform Services | D84: Sonrisa | E84: 197976 | F84: IdomSoft - Faker Microsite Platform | G84: s2s vpn, app gw issues | H84: 46119 | K84: 2 | L84: Billable work
A85: Zsolt Tornai | B85: CPS | C85: Cloud Platform Services | D85: Sonrisa | E85: 186698 | F85: greeHill | G85: Create Locally runnable Airflow 3 | H85: 46119 | K85: 8 | L85: Billable work
A86: Alexander Póda | B86: CPS | C86: Cloud Platform Services | D86: Sonrisa | E86: 196631 | F86: Diligent - ARC BOS Sunset | G86: cisco robot test | H86: 46119 | K86: 8 | L86: Billable work
A87: Ferenc Beder | B87: CPS | C87: Lufthansa Netline - Crew | D87: Lufthansa | F87: General development | H87: 46119 | K87: 8 | L87: Billable work
A88: Marcell Kovács | B88: CPS | C88: Other | D88: Sonrisa | F88: Paid leave | H88: 46119 | K88: 8 | L88: Non-work activity
A89: Alexandru Ceclan | B89: CPS | C89: Other | D89: Sonrisa | F89: Paid leave | H89: 46119 | K89: 6 | L89: Non-work activity
A90: Márk-Ádám Vaida | B90: CPS | C90: Cloud Platform Services | D90: Sonrisa | E90: 189341 | F90: MVMI | G90: CI/CD | H90: 46119 | K90: 4.5 | L90: Billable work
A91: Márk-Ádám Vaida | B91: CPS | C91: CPS Support | D91: Sonrisa | E91: 195325 | F91: MVMI OMNI - general availability collector ticket | H91: 46119 | K91: 10 | L91: Billable work
A92: Attila Kovács | B92: CPS | C92: Jumio AWS | D92: Jumio | E92: 181325 | F92: Development and operations | H92: 46119 | K92: 8 | L92: Billable work
A93: Zoltán Szántó | B93: CPS | C93: Cloud Platform Services | D93: Sonrisa | E93: 186697 | F93: Bayer | H93: 46119 | K93: 8 | L93: Billable work
A94: Botond Gáll | B94: CPS | C94: Cloud Platform Services | D94: Sonrisa | E94: 193502 | F94: ColosseumDental | G94: opencode ramp up Bencével | H94: 46119 | K94: 2 | L94: Billable work
A95: Botond Gáll | B95: CPS | C95: Cloud Platform Services | D95: Sonrisa | E95: 196190 | F95: DirectTravel | H95: 46119 | K95: 4 | L95: Billable work
A96: Botond Gáll | B96: CPS | C96: CPS Support | D96: Sonrisa | E96: 195325 | F96: MVMI OMNI - general availability collector ticket | H96: 46119 | K96: 8 | L96: Billable work
A97: Botond Gáll | B97: CPS | C97: Cloud Platform Services | D97: Sonrisa | E97: 188599 | F97: Sonrisa Sys | H97: 46119 | K97: 2 | L97: Billable work
A98: Zoltán Szántó | B98: CPS | C98: CPS Support | D98: Sonrisa | E98: 195325 | F98: MVMI OMNI - general availability collector ticket | H98: 46119 | K98: 6 | L98: Billable work
A99: Dániel Molnár | B99: CPS | C99: Cloud Platform Services | D99: Sonrisa | E99: 186698 | F99: greeHill | H99: 46119 | K99: 2 | L99: Billable work
A100: Dániel Molnár | B100: CPS | C100: Cloud Platform Services | D100: Sonrisa | E100: 196190 | F100: DirectTravel | H100: 46119 | K100: 2 | L100: Billable work
...

Sheet Team
A1: Name | B1: Site | C1: Status | D1: Level | E1: Position
A2: Alexander Póda | B2: BUD | C2: Available | D2: E7 | E2: =IF(D2="E1","Junior", IF(D2="E2","Junior", IF(D2="E3","Expert", IF(D2="E4","Expert", IF(D2="E5","Advanced", IF(D2="E6","Senior", IF(D2="E7","Senior", IF(D2="E8","Lead", IF(D2="E9","Lead","") ) ) ) ) ) ) ) ) -> Senior
A3: Péter Bakonyi | B3: SZEG | C3: Available | D3: E6 | E3: =IF(D3="E1","Junior", IF(D3="E2","Junior", IF(D3="E3","Expert", IF(D3="E4","Expert", IF(D3="E5","Advanced", IF(D3="E6","Senior", IF(D3="E7","Senior", IF(D3="E8","Lead", IF(D3="E9","Lead","") ) ) ) ) ) ) ) ) -> Senior
A4: Gergely Peidl | B4: BUD | C4: Available | D4: E8 | E4: =IF(D4="E1","Junior", IF(D4="E2","Junior", IF(D4="E3","Expert", IF(D4="E4","Expert", IF(D4="E5","Advanced", IF(D4="E6","Senior", IF(D4="E7","Senior", IF(D4="E8","Lead", IF(D4="E9","Lead","") ) ) ) ) ) ) ) ) -> Lead
A5: Alexandru Ceclan | B5: MVH | C5: Available | D5: E8 | E5: =IF(D5="E1","Junior", IF(D5="E2","Junior", IF(D5="E3","Expert", IF(D5="E4","Expert", IF(D5="E5","Advanced", IF(D5="E6","Senior", IF(D5="E7","Senior", IF(D5="E8","Lead", IF(D5="E9","Lead","") ) ) ) ) ) ) ) ) -> Lead
A6: Attila Jankó-Király | B6: PCS | C6: Available | D6: E7 | E6: =IF(D6="E1","Junior", IF(D6="E2","Junior", IF(D6="E3","Expert", IF(D6="E4","Expert", IF(D6="E5","Advanced", IF(D6="E6","Senior", IF(D6="E7","Senior", IF(D6="E8","Lead", IF(D6="E9","Lead","") ) ) ) ) ) ) ) ) -> Senior
A7: Attila Kovács | B7: MVH | C7: Available | D7: E5 | E7: =IF(D7="E1","Junior", IF(D7="E2","Junior", IF(D7="E3","Expert", IF(D7="E4","Expert", IF(D7="E5","Advanced", IF(D7="E6","Senior", IF(D7="E7","Senior", IF(D7="E8","Lead", IF(D7="E9","Lead","") ) ) ) ) ) ) ) ) -> Advanced
A8: Zsolt Tornai | B8: MVH | C8: Available | D8: E4 | E8: =IF(D8="E1","Junior", IF(D8="E2","Junior", IF(D8="E3","Expert", IF(D8="E4","Expert", IF(D8="E5","Advanced", IF(D8="E6","Senior", IF(D8="E7","Senior", IF(D8="E8","Lead", IF(D8="E9","Lead","") ) ) ) ) ) ) ) ) -> Expert
A9: Bálint Lajos Török | B9: MVH | C9: Available | D9: E5 | E9: =IF(D9="E1","Junior", IF(D9="E2","Junior", IF(D9="E3","Expert", IF(D9="E4","Expert", IF(D9="E5","Advanced", IF(D9="E6","Senior", IF(D9="E7","Senior", IF(D9="E8","Lead", IF(D9="E9","Lead","") ) ) ) ) ) ) ) ) -> Advanced
A10: Márk-Ádám Vaida | B10: MVH | C10: Available | D10: E4 | E10: =IF(D10="E1","Junior", IF(D10="E2","Junior", IF(D10="E3","Expert", IF(D10="E4","Expert", IF(D10="E5","Advanced", IF(D10="E6","Senior", IF(D10="E7","Senior", IF(D10="E8","Lead", IF(D10="E9","Lead","") ) ) ) ) ) ) ) ) -> Expert
A11: Dávid Pap | B11: BUD | C11: Available | D11: E1 | E11: =IF(D11="E1","Junior", IF(D11="E2","Junior", IF(D11="E3","Expert", IF(D11="E4","Expert", IF(D11="E5","Advanced", IF(D11="E6","Senior", IF(D11="E7","Senior", IF(D11="E8","Lead", IF(D11="E9","Lead","") ) ) ) ) ) ) ) ) -> Junior
A12: Botond Gáll | B12: MVH | C12: Available | D12: E1 | E12: =IF(D12="E1","Junior", IF(D12="E2","Junior", IF(D12="E3","Expert", IF(D12="E4","Expert", IF(D12="E5","Advanced", IF(D12="E6","Senior", IF(D12="E7","Senior", IF(D12="E8","Lead", IF(D12="E9","Lead","") ) ) ) ) ) ) ) ) -> Junior
A13: Marcell Kovács | B13: BUD | C13: Future | D13: E3 | E13: =IF(D13="E1","Junior", IF(D13="E2","Junior", IF(D13="E3","Expert", IF(D13="E4","Expert", IF(D13="E5","Advanced", IF(D13="E6","Senior", IF(D13="E7","Senior", IF(D13="E8","Lead", IF(D13="E9","Lead","") ) ) ) ) ) ) ) ) -> Expert
A14: Zoltán Szántó | B14: MVH | C14: Future | D14: E8 | E14: =IF(D14="E1","Junior", IF(D14="E2","Junior", IF(D14="E3","Expert", IF(D14="E4","Expert", IF(D14="E5","Advanced", IF(D14="E6","Senior", IF(D14="E7","Senior", IF(D14="E8","Lead", IF(D14="E9","Lead","") ) ) ) ) ) ) ) ) -> Lead
A15: Dániel Molnár | B15: BUD | D15: e8 | E15: =IF(D15="E1","Junior", IF(D15="E2","Junior", IF(D15="E3","Expert", IF(D15="E4","Expert", IF(D15="E5","Advanced", IF(D15="E6","Senior", IF(D15="E7","Senior", IF(D15="E8","Lead", IF(D15="E9","Architect","") ) ) ) ) ) ) ) ) -> Lead
A16: István Bánfi | D16: e9 | E16: Contractor
A17: Ferenc Beder | D17: e7 | E17: PartTime
A18: Andor Szabó | D18: e3 | E18: Contractor

Sheet Sheet2
A2: Company name | B2: Team | C2: Task name | D2: User | E2: Sum of Length
A3: IdomSoft Zrt. | E3: 20
A4: Jumio | E4: 160
A5: Lufthansa | E5: 160
A6: NKP | E6: 2
A7: Sonrisa | B7: CPS | C7: Aws Inference Farm | E7: 23
C8: Bayer | E8: 118.5
C9: ColosseumDental | D9: Botond Gáll | E9: 17
D10: Marcell Kovács | E10: 30.25
D11: Zoltán Szántó | E11: 4
C12: ColosseumDental Total | E12: 51.25
C13: Deutsche Telekom | E13: 1
C14: DevOps Guild activities | E14: 1.5
C15: Diligent - ARC BOS Sunset | E15: 302.5
C16: DirectTravel | E16: 109.5
C17: General Research | E17: 22
C18: greeHill | E18: 220.75
C19: IdomSoft - Faker Microsite Platform | E19: 37.5
C20: Internal Systems | E20: 39
C21: Interviews | E21: 12.75
C22: Learning | E22: 6.25
C23: Meeting | E23: 84.75
C24: MVMI | D24: Bálint Lajos Török | E24: 0.5
D25: Botond Gáll | E25: 0.5
D26: Ferenc Beder | E26: 6
D27: Márk-Ádám Vaida | E27: 20.75
D28: Zoltán Szántó | E28: 6.5
C29: MVMI Total | E29: 34.25
C30: MVMI OMNI - general availability collector ticket | E30: 526
C31: Observer | E31: 234.25
C32: OKFŐ | E32: 10
C33: Onriva: Incidents , New features | E33: 29
C34: Onriva: Availability, Monitoring, Meetings | E34: 66.25
C35: Paid leave | E35: 96
C36: Power automate | E36: 19.5
C37: ProSharp - OTEL | E37: 75.25
C38: SocialBud : Incidents , New features | D38: Marcell Kovács | E38: 6
C39: SocialBud : Incidents , New features Total | E39: 6
C40: SocialBud: Availability, Monitoring, Meetings | D40: Alexander Póda | E40: 1.75
C41: SocialBud: Availability, Monitoring, Meetings Total | E41: 1.75
C42: Sonrisa Sys | D42: Botond Gáll | E42: 4
C43: Sonrisa Sys Total | E43: 4
B44: CPS Total | E44: 2132.5
A45: Sonrisa Total | E45: 2132.5
A46: Spinwheel | B46: CPS | C46: PM task | D46: István Bánfi | E46: 3.5
C47: PM task Total | E47: 3.5
C48: SIL-159 - NATS JetStream Deployment | D48: István Bánfi | E48: 3
C49: SIL-159 - NATS JetStream Deployment Total | E49: 3
C50: SIL-304 - Create Bitbucket Pipeline to build and push | D50: István Bánfi | E50: 6.5
C51: SIL-304 - Create Bitbucket Pipeline to build and push Total | E51: 6.5
C52: SIL-315 - Define ExternalSecret for each service | D52: István Bánfi | E52: 2
C53: SIL-315 - Define ExternalSecret for each service Total | E53: 2
C54: SIL-328 - SpinWheel DSM | D54: István Bánfi | E54: 11
C55: SIL-328 - SpinWheel DSM Total | E55: 11
C56: SIL-329 - Project Preparation | D56: István Bánfi | E56: 14
C57: SIL-329 - Project Preparation Total | E57: 14
C58: SIL-330 - Internal Meeting | D58: István Bánfi | E58: 2.5
C59: SIL-330 - Internal Meeting Total | E59: 2.5
C60: SIL-331 - Technical Discussion | D60: István Bánfi | E60: 8.5
C61: SIL-331 - Technical Discussion Total | E61: 8.5
C62: SIL-333 - Workshops | D62: István Bánfi | E62: 1
C63: SIL-333 - Workshops Total | E63: 1
C64: SIL-363 - INFRA: Implement additional EKS components | D64: István Bánfi | E64: 9.5
C65: SIL-363 - INFRA: Implement additional EKS components Total | E65: 9.5
C66: SIL-395 - Create K8s+Helm+Scaffold dev environment for the SCM | D66: István Bánfi | E66: 1
C67: SIL-395 - Create K8s+Helm+Scaffold dev environment for the SCM Total | E67: 1
C68: SIL-426 - Include Code Artifact Token in Pipeline Step | D68: István Bánfi | E68: 2
C69: SIL-426 - Include Code Artifact Token in Pipeline Step Total | E69: 2
C70: SIL-434 - Containerization | D70: István Bánfi | E70: 2
C71: SIL-434 - Containerization Total | E71: 2
C72: SIL-435 - Configuration and Secrets Management | D72: István Bánfi | E72: 2
C73: SIL-435 - Configuration and Secrets Management Total | E73: 2
C74: SIL-62 - SAM: Local Configuration and Secrets Management | D74: István Bánfi | E74: 5
C75: SIL-62 - SAM: Local Configuration and Secrets Management Total | E75: 5
B76: CPS Total | E76: 73.5
A77: Spinwheel Total | E77: 73.5
A78: Synlab | B78: CPS | C78: SD-740 - Clean-up unused domains from Azure Front Door Origin Groups in DEV and Stage environments | D78: Dániel Molnár | E78: 1
D79: Zsolt Tornai | E79: 24
C80: SD-740 - Clean-up unused domains from Azure Front Door Origin Groups in DEV and Stage environments Total | E80: 25
C81: SD-742 - Implement Timebound Access Controls and Access Justification System for Results data in Mon | D81: Dániel Molnár | E81: 4
D82: Marcell Kovács | E82: 32.25
C83: SD-742 - Implement Timebound Access Controls and Access Justification System for Results data in Mon Total | E83: 36.25
C84: SD-745 - MongoDB Atlas Private Link Implementation | D84: Zsolt Tornai | E84: 8
C85: SD-745 - MongoDB Atlas Private Link Implementation Total | E85: 8
B86: CPS Total | E86: 69.25
A87: Synlab Total | E87: 69.25
A88: Grand Total | E88: 2617.25

Sheet Sheet1
A2: Company name | B2: User | C2: Task name | D2: Sum of Length
A3: IdomSoft Zrt. | D3: 20
A4: Jumio | D4: 160
A5: Lufthansa | D5: 160
A6: NKP | D6: 2
A7: Sonrisa | B7: Alexander Póda | C7: Aws Inference Farm | D7: 1.5
C8: Diligent - ARC BOS Sunset | D8: 57.75
C9: Internal Systems | D9: 1
C10: Interviews | D10: 4
C11: Meeting | D11: 3.5
C12: Observer | D12: 90.5
C13: SocialBud: Availability, Monitoring, Meetings | D13: 1.75
B14: Alexander Póda Total | D14: 160
B15: Alexandru Ceclan | C15: Aws Inference Farm | D15: 15
C16: Interviews | D16: 3.5
C17: Meeting | D17: 9
C18: Observer | D18: 109
B19: Alexandru Ceclan Total | D19: 136.5
B20: Andor Szabó | C20: Diligent - ARC BOS Sunset | D20: 40
B21: Andor Szabó Total | D21: 40
B22: Bálint Lajos Török | C22: Bayer | D22: 30.5
C23: Diligent - ARC BOS Sunset | D23: 48.5
C24: IdomSoft - Faker Microsite Platform | D24: 37.5
C25: Internal Systems | D25: 5
C26: Interviews | D26: 1
C27: Meeting | D27: 5
C28: MVMI | D28: 0.5
C29: MVMI OMNI - general availability collector ticket | D29: 96
C30: Paid leave | D30: 32
B31: Bálint Lajos Török Total | D31: 256
B32: Botond Gáll | C32: Aws Inference Farm | D32: 1
C33: ColosseumDental | D33: 17
C34: DirectTravel | D34: 60.5
C35: Interviews | D35: 3.25
C36: Meeting | D36: 6.75
C37: MVMI | D37: 0.5
C38: MVMI OMNI - general availability collector ticket | D38: 92
C39: Onriva: Incidents , New features | D39: 6
C40: Onriva: Availability, Monitoring, Meetings | D40: 32
C41: Paid leave | D41: 8
C42: Power automate | D42: 19.5
C43: Sonrisa Sys | D43: 4
B44: Botond Gáll Total | D44: 250.5
B45: Dániel Molnár | C45: DirectTravel | D45: 49
C46: General Research | D46: 22
C47: greeHill | D47: 42.5
C48: Interviews | D48: 1
C49: Meeting | D49: 40.5
B50: Dániel Molnár Total | D50: 155
B51: Dávid Pap | C51: Diligent - ARC BOS Sunset | D51: 156.25
C52: Meeting | D52: 3.75
C53: MVMI OMNI - general availability collector ticket | D53: 124
B54: Dávid Pap Total | D54: 284
B55: Ferenc Beder | C55: MVMI | D55: 6
B56: Ferenc Beder Total | D56: 6
B57: István Bánfi | C57: Deutsche Telekom | D57: 1
C58: Internal Systems | D58: 9
C59: Meeting | D59: 4.5
C60: Observer | D60: 14.75
B61: István Bánfi Total | D61: 29.25
B62: Marcell Kovács | C62: ColosseumDental | D62: 30.25
C63: greeHill | D63: 72.25
C64: Learning | D64: 0.5
C65: Meeting | D65: 2.75
C66: Paid leave | D66: 16
C67: SocialBud : Incidents , New features | D67: 6
B68: Marcell Kovács Total | D68: 127.75
B69: Márk-Ádám Vaida | C69: Aws Inference Farm | D69: 5.5
C70: Internal Systems | D70: 24
C71: Learning | D71: 5.75
C72: Meeting | D72: 3
C73: MVMI | D73: 20.75
C74: MVMI OMNI - general availability collector ticket | D74: 118
C75: Onriva: Incidents , New features | D75: 23
C76: Onriva: Availability, Monitoring, Meetings | D76: 34.25
C77: ProSharp - OTEL | D77: 43.75
B78: Márk-Ádám Vaida Total | D78: 278
B79: Péter Bakonyi | C79: Meeting | D79: 4
C80: Observer | D80: 20
B81: Péter Bakonyi Total | D81: 24
B82: Zoltán Szántó | C82: Bayer | D82: 88
C83: ColosseumDental | D83: 4
C84: DevOps Guild activities | D84: 1.5
C85: MVMI | D85: 6.5
C86: MVMI OMNI - general availability collector ticket | D86: 96
C87: Paid leave | D87: 32
C88: ProSharp - OTEL | D88: 31.5
B89: Zoltán Szántó Total | D89: 259.5
B90: Zsolt Tornai | C90: greeHill | D90: 106
C91: Meeting | D91: 2
C92: OKFŐ | D92: 10
C93: Paid leave | D93: 8
B94: Zsolt Tornai Total | D94: 126
A95: Sonrisa Total | D95: 2132.5
A96: Spinwheel | B96: István Bánfi | C96: PM task | D96: 3.5
C97: SIL-159 - NATS JetStream Deployment | D97: 3
C98: SIL-304 - Create Bitbucket Pipeline to build and push | D98: 6.5
C99: SIL-315 - Define ExternalSecret for each service | D99: 2
C100: SIL-328 - SpinWheel DSM | D100: 11
C101: SIL-329 - Project Preparation | D101: 14
...

Sheet Sheet3
A1: Total hours | B1: (Multiple Items)
A3: User | B3: Sum of Length
A4: Alexander Póda | B4: 160
A5: Alexandru Ceclan | B5: 136.5
A6: Andor Szabó | B6: 40
A7: Attila Kovács | B7: 160
A8: Bálint Lajos Török | B8: 128
A9: Botond Gáll | B9: 150.5
A10: Dániel Molnár | B10: 138
A11: Dávid Pap | B11: 160
A12: Ferenc Beder | B12: 6
A13: István Bánfi | B13: 119.25
A14: Marcell Kovács | B14: 144
A15: Márk-Ádám Vaida | B15: 160
... A19: Grand Total | B19: 1809.75
A22: Internal hours | B22: (Multiple Items) | D22: Internal hours | E22: MVMI OMNI - general availability collector ticket | G22: Internal hours | H22: Paid leave | J22: User | K22: István Bánfi | M22: User | N22: Andor Szabó
A24: User | B24: Sum of Length | D24: User | E24: Sum of Length | G24: User | H24: Sum of Length | J24: Project name | K24: Sum of Length | M24: Project name | N24: Sum of Length
A25: Alexander Póda | B25: 8.5 | D25: Bálint Lajos Török | E25: 96 | G25: Bálint Lajos Török | H25: 32 | J25: Cloud Platform Services | K25: 28.25 | M25: Cloud Platform Services | N25: 40
A26: Alexandru Ceclan | B26: 12.5 | D26: Botond Gáll | E26: 92 | G26: Botond Gáll | H26: 8 | J26: Idomsoft - Legacy költöztetés | K26: 20 | M26: Grand Total | N26: 40
A27: Bálint Lajos Török | B27: 11 | D27: Dávid Pap | E27: 124 | G27: Marcell Kovács | H27: 16 | J27: Silver 3.0 | K27: 73.5
A28: Botond Gáll | B28: 10 | D28: Márk-Ádám Vaida | E28: 118 | G28: Zoltán Szántó | H28: 32 | J28: Sonrisa Presales | K28: 1
A29: Dániel Molnár | B29: 63.5 | D29: Zoltán Szántó | E29: 96 | G29: Zsolt Tornai | H29: 8 | J29: Grand Total | K29: 122.75
A30: Dávid Pap | B30: 3.75 | D30: Grand Total | E30: 526 | G30: Grand Total | H30: 96
A31: István Bánfi | B31: 31.5
A32: Marcell Kovács | B32: 3.25
A33: Márk-Ádám Vaida | B33: 32.75
A34: Péter Bakonyi | B34: 4
A35: Zsolt Tornai | B35: 2
A36: Grand Total | B36: 182.75
